NetkillerJavaFix1/README.md
NetkillerJavaFix1/__init__.py
NetkillerJavaFix1/__main__.py
NetkillerJavaFix1/file.epub
NetkillerJavaFix1/index.html
NetkillerJavaFix1/css/__init__.py
NetkillerJavaFix1/css/annotations.css
NetkillerJavaFix1/css/main.css
NetkillerJavaFix1/css/normalize.css
NetkillerJavaFix1/css/popup.css
NetkillerJavaFix1/font/__init__.py
NetkillerJavaFix1/font/fontello.eot
NetkillerJavaFix1/font/fontello.svg
NetkillerJavaFix1/font/fontello.ttf
NetkillerJavaFix1/font/fontello.woff
NetkillerJavaFix1/img/__init__.py
NetkillerJavaFix1/img/annotator-glyph-sprite.png
NetkillerJavaFix1/img/annotator-icon-sprite.png
NetkillerJavaFix1/img/apple-touch-icon.png
NetkillerJavaFix1/img/cancelfullscreen.png
NetkillerJavaFix1/img/close.png
NetkillerJavaFix1/img/fullscreen.png
NetkillerJavaFix1/img/loader.gif
NetkillerJavaFix1/img/menu-icon.png
NetkillerJavaFix1/img/save.png
NetkillerJavaFix1/img/saved.png
NetkillerJavaFix1/img/settings-s.png
NetkillerJavaFix1/img/settings.png
NetkillerJavaFix1/img/star.png
NetkillerJavaFix1/js/__init__.py
NetkillerJavaFix1/js/epub.js
NetkillerJavaFix1/js/epub.min.js
NetkillerJavaFix1/js/epub.min.map
NetkillerJavaFix1/js/hooks.min.js
NetkillerJavaFix1/js/hooks.min.map
NetkillerJavaFix1/js/reader.js
NetkillerJavaFix1/js/reader.js.map
NetkillerJavaFix1/js/reader.min.js
NetkillerJavaFix1/js/reader.min.map
NetkillerJavaFix1/js/hooks/__init__.py
NetkillerJavaFix1/js/hooks/extensions/__init__.py
NetkillerJavaFix1/js/hooks/extensions/highlight.js
NetkillerJavaFix1/js/libs/__init__.py
NetkillerJavaFix1/js/libs/jquery.min.js
NetkillerJavaFix1/js/libs/localforage.min.js
NetkillerJavaFix1/js/libs/screenfull.js
NetkillerJavaFix1/js/libs/screenfull.min.js
NetkillerJavaFix1/js/libs/zip.min.js
NetkillerJavaFix1/js/plugins/__init__.py
NetkillerJavaFix1/js/plugins/hypothesis.js
NetkillerJavaFix1/js/plugins/search.js
netkiller_java_fix1-2025.3.24.1.dist-info/METADATA
netkiller_java_fix1-2025.3.24.1.dist-info/WHEEL
netkiller_java_fix1-2025.3.24.1.dist-info/entry_points.txt
netkiller_java_fix1-2025.3.24.1.dist-info/top_level.txt
netkiller_java_fix1-2025.3.24.1.dist-info/RECORD
